{
	"type": "FeatureCollection",
	"features": [
		{
			"type": "Feature",
			"properties": {
				"name": "Tag4 stanzino",
				"description": "tag di prova posizionato nello stanzino",
				"flat": 4
			},
			"geometry": {
				"coordinates": [14.972861207537079, 40.61715021229716],
				"type": "Point"
			},
			"id": 757
		}
	]
}
